setup.py
easyhistory/__init__.py
easyhistory/api.py
easyhistory/day.py
easyhistory/helpers.py
easyhistory/history.py
easyhistory/store.py
easyhistory.egg-info/PKG-INFO
easyhistory.egg-info/SOURCES.txt
easyhistory.egg-info/dependency_links.txt
easyhistory.egg-info/requires.txt
easyhistory.egg-info/top_level.txt