Metadata-Version: 1.1
Name: easyhistory
Version: 0.0.1
Summary: A utility for rqalpha history
Home-page: https://github.com/shidenggui/easyhistory
Author: shidenggui
Author-email: longlyshidenggui@gmail.com
License: BSD
Keywords: China stock trade
Platform: UNKNOWN
Classifier: Development Status :: 4 - Beta
Classifier: Programming Language :: Python :: 2.6
Classifier: Programming Language :: Python :: 2.7
Classifier: Programming Language :: Python :: 3.2
Classifier: Programming Language :: Python :: 3.3
Classifier: Programming Language :: Python :: 3.4
Classifier: Programming Language :: Python :: 3.5
Classifier: License :: OSI Approved :: BSD License
